automagic/__init__.py
automagic/automagic.py
automagic/cli.py
automagic-0.0.1.dist-info/LICENSE
automagic-0.0.1.dist-info/METADATA
automagic-0.0.1.dist-info/WHEEL
automagic-0.0.1.dist-info/top_level.txt
automagic-0.0.1.dist-info/RECORD
