Metadata-Version: 2.1
Name: automagic
Version: 0.0.1
Summary: Opinionated ML tooling for rapid R&D.
Author-email: Automagic ML <hi@automagic.ml>
Maintainer-email: Automagic ML <hi@automagic.ml>
License: GNU General Public License v3
Project-URL: bugs, https://github.com/automagicml/automagic-sdk/issues
Project-URL: changelog, https://github.com/automagicml/automagic-sdk/blob/master/changelog.md
Project-URL: homepage, https://github.com/automagicml/automagic-sdk
License-File: LICENSE
Requires-Dist: typer
Provides-Extra: dev
Requires-Dist: coverage; extra == "dev"
Requires-Dist: mypy; extra == "dev"
Requires-Dist: pytest; extra == "dev"
Requires-Dist: ruff; extra == "dev"
